cyberfusion/Common/Config.py
cyberfusion/Common/Filesystem.py
cyberfusion/Common/FilesystemComparison.py
cyberfusion/Common/__init__.py
cyberfusion/Common/exceptions/__init__.py
python3_cyberfusion_common-2.12.1.dist-info/METADATA
python3_cyberfusion_common-2.12.1.dist-info/WHEEL
python3_cyberfusion_common-2.12.1.dist-info/top_level.txt
python3_cyberfusion_common-2.12.1.dist-info/RECORD
