Metadata-Version: 2.4
Name: python3-cyberfusion-common
Version: 2.12.1
Summary: Common utilities.
Author-email: Cyberfusion <support@cyberfusion.io>
Project-URL: Source, https://github.com/CyberfusionIO/python3-cyberfusion-common
Requires-Dist: psutil==7.0.0
Requires-Dist: requests==2.32.3
